setup.py
src/digimat/__init__.py
src/digimat.pronoo.egg-info/PKG-INFO
src/digimat.pronoo.egg-info/SOURCES.txt
src/digimat.pronoo.egg-info/dependency_links.txt
src/digimat.pronoo.egg-info/namespace_packages.txt
src/digimat.pronoo.egg-info/not-zip-safe
src/digimat.pronoo.egg-info/requires.txt
src/digimat.pronoo.egg-info/top_level.txt
src/digimat/pronoo/__init__.py
src/digimat/pronoo/pronoo.py