Metadata-Version: 1.0
Name: digimat.pronoo
Version: 0.1.10
Summary: Digimat Pronoo
Home-page: http://www.digimat.ch
Author: Frederic Hess
Author-email: fhess@splust.ch
License: PSF
Platform: UNKNOWN
